polyenv/__init__.py
polyenv/__main__.py
polyenv-0.1.0.dist-info/METADATA
polyenv-0.1.0.dist-info/RECORD
polyenv-0.1.0.dist-info/WHEEL
polyenv-0.1.0.dist-info/entry_points.txt
polyenv-0.1.0.dist-info/top_level.txt
