Metadata-Version: 2.1
Name: polyenv
Version: 0.1.0
Summary: Run any programming language
Home-page: https://github.com/FrankKair/polyenv
Author: Frank Kair
Author-email: frankkair@gmail.com
License: MIT
Download-URL: https://pypi.python.org/pypi/polyenv
Platform: any
Requires-Dist: pytio
